MANIFEST.in
README.rst
setup.py
docs/HISTORY.txt
docs/LICENSE.txt
docs/stxnext.grayscale.example.png
src/stxnext/__init__.py
src/stxnext.grayscale.egg-info/PKG-INFO
src/stxnext.grayscale.egg-info/SOURCES.txt
src/stxnext.grayscale.egg-info/dependency_links.txt
src/stxnext.grayscale.egg-info/entry_points.txt
src/stxnext.grayscale.egg-info/namespace_packages.txt
src/stxnext.grayscale.egg-info/not-zip-safe
src/stxnext.grayscale.egg-info/requires.txt
src/stxnext.grayscale.egg-info/top_level.txt
src/stxnext/grayscale/__init__.py
src/stxnext/grayscale/config.py
src/stxnext/grayscale/configure.zcml
src/stxnext/grayscale/event.zcml
src/stxnext/grayscale/events.py
src/stxnext/grayscale/utils.py
src/stxnext/grayscale/version.txt
src/stxnext/grayscale/browser/__init__.py
src/stxnext/grayscale/browser/configure.zcml
src/stxnext/grayscale/browser/icon.png
src/stxnext/grayscale/browser/preferences/__init__.py
src/stxnext/grayscale/browser/preferences/configure.zcml
src/stxnext/grayscale/browser/preferences/grayscale_settings.py
src/stxnext/grayscale/locales/stxnext.grayscale.pot
src/stxnext/grayscale/locales/pl/LC_MESSAGES/stxnext.grayscale.po
src/stxnext/grayscale/profiles/default/actionicons.xml
src/stxnext/grayscale/profiles/default/controlpanel.xml
src/stxnext/grayscale/profiles/default/metadata.xml
src/stxnext/grayscale/profiles/default/propertiestool.xml
src/stxnext/grayscale/tests/__init__.py
src/stxnext/grayscale/tests/base.py
src/stxnext/grayscale/tests/grayscale.txt
src/stxnext/grayscale/tests/test_doctests.py
src/stxnext/grayscale/tests/test_utils.py