Metadata-Version: 1.0
Name: stxnext.grayscale
Version: 1.0.0
Summary: Plone add-on product for displaying the content in grayscale.
Home-page: http://stxnext.pl/open-source
Author: STX Next Sp. z o.o.
Author-email: info@stxnext.pl
License: Zope Public License, Version 2.1 (ZPL)
Keywords: plone grayscale images
Platform: Any
Classifier: Framework :: Zope2
Classifier: Framework :: Plone
Classifier: Intended Audience :: Developers
Classifier: License :: OSI Approved :: Zope Public License
Classifier: Natural Language :: English
Classifier: Programming Language :: Python
